{
  "acronyms": {
    "IO": "investigating officer",
    "TPU": "troop program unit",
    "ARNG": "Army National Guard",
    "USAR": "U.S. Army Reserve",
    "BA": "battle assembly",

    "AC": "active component",
    "RC": "reserve component",
    "AGR": "active guard reserve",
    "AD": "active duty",
    "ADSW": "active duty for special work",
    "ADT": "active duty for training",
    "AT": "annual training",
    "IDT": "inactive duty training",

    "CO": "company",
    "BN": "battalion",
    "BDE": "brigade",
    "DIV": "division",
    "CORPS": "corps",
    "HQ": "headquarters",
    "HHC": "headquarters and headquarters company",
    "HHD": "headquarters and headquarters detachment",

    "CDR": "commander",
    "OIC": "officer in charge",
    "NCO": "noncommissioned officer",
    "NCOIC": "noncommissioned officer in charge",
    "SNCO": "senior noncommissioned officer",
    "CSM": "command sergeant major",
    "SGM": "sergeant major",
    "1SG": "first sergeant",
    "PSG": "platoon sergeant",
    "PL": "platoon leader",
    "XO": "executive officer",

    "S1": "personnel section",
    "S2": "intelligence section",
    "S3": "operations and training section",
    "S4": "logistics section",
    "S6": "communications/electronics section",
    "G1": "personnel staff (general staff level)",
    "G2": "intelligence staff (general staff level)",
    "G3": "operations and training staff (general staff level)",
    "G4": "logistics staff (general staff level)",
    "G6": "communications/electronics staff (general staff level)",

    "HQDA": "Headquarters, Department of the Army",
    "FORSCOM": "U.S. Army Forces Command",
    "TRADOC": "U.S. Army Training and Doctrine Command",
    "USARC": "U.S. Army Reserve Command",
    "MEDCOM": "U.S. Army Medical Command",
    "INSCOM": "U.S. Army Intelligence and Security Command",
    "AMC": "U.S. Army Materiel Command",

    "AR": "Army regulation; agent report; armor",
    "DA": "Department of the Army",
    "DoD": "Department of Defense",
    "UCMJ": "Uniform Code of Military Justice",
    "MFR": "memorandum for record",
    "POC": "point of contact",
    "OPORD": "operations order",
    "FRAGO": "fragmentary order",
    "WARNO": "warning order",
    "SOP": "standard operating procedure",

    "MOS": "military occupational specialty",
    "PME": "professional military education",
    "NCOPD": "noncommissioned officer professional development",
    "OES": "officer education system",
    "NCOES": "noncommissioned officer education system",

    "APFT": "Army Physical Fitness Test",
    "ACFT": "Army Combat Fitness Test",
    "PT": "physical training",
    "HRC": "Human Resources Command",
    "SRP": "soldier readiness processing",
    "MOB": "mobilization",
    "DEMOB": "demobilization",

    "FOUO": "for official use only",
    "SSI": "shoulder sleeve insignia",
    "ASU": "Army Service Uniform",
    "OER": "officer evaluation report",
    "NCOER": "noncommissioned officer evaluation report",
    "AWOL": "absent without leave",
    "LOI": "letter of instruction",
    "LOA": "letter of admonition",
    "LOC": "letter of concern",
    "GOMOR": "general officer memorandum of reprimand",

    "CID": "Criminal Investigation Division",
    "MP": "military police",
    "JAG": "Judge Advocate General's Corps",

    "ROE": "rules of engagement",
    "COC": "code of conduct",
    "COIN": "counterinsurgency",
    "COF": "course of fire",
    "COA": "course of action",

    "BCT": "brigade combat team",
    "IBCT": "infantry brigade combat team",
    "SBCT": "Stryker brigade combat team",
    "ABCT": "armored brigade combat team",

    "TOC": "tactical operations center",
    "FOB": "forward operating base",
    "COP": "combat outpost",
    "FARP": "forward arming and refueling point",

    "DFAS": "Defense Finance and Accounting Service",
    "LES": "leave and earnings statement",
    "BAS": "basic allowance for subsistence",
    "BAH": "basic allowance for housing",
    "PCS": "permanent change of station",
    "TDY": "temporary duty",

    "APW": "American prisoner of war",
    "APWIB": "American Prisoner of War Information Bureau",
    "APWIB (Br)": "Branch American Prisoner of War Information Bureau",
    "AQB": "Army Qualification Battery",
    "AQL": "acceptable quality level",
    "ARA": "aerial rocket artillery; assigned responsible agency",
    "ARAAV": "armored reconnaissance airborne assault vehicle",
    "ARAC": "Army radar approach control",
    "ARAV": "Army aviator",
    "ARAVBAD": "Army Aviator Badge",
    "ARB": "armored rifle battalion",
    "ARCAM": "Army Reserve Components Achievement Medal",
    "ARC": "accounting requirements code",
    "ARCE": "amphibious river crossing equipment (French)",
    "ARCHS": "Army Reactor Systems Health and Safety Review Committee",
    "ARCO": "Army Requirements Control Office",
    "ARCOM": "United States Army Reserve Command; Army Commendation Medal",
    "ARCOTR": "Army Reserve Components Overseas Training Ribbon",
    "ARCSA": "aviation requirements for the combat structure of the Army",
    "ARCT": "Army Radio Code Aptitude Test",
    "ARD": "automatic release date",
    "ARDC": "United States Army Armament Research and Development Center",
    "ARDEMS": "artillery delivered multi-purpose submunition",
    "ARDIS": "Army RDTE Information System",
    "ARDME": "automatic radar data measuring equipment",
    "ARDP": "Army Requirements Development Plan",
    "AREPT": "agent report",
    "ARFA": "Allied Radio Frequency Agency",
    "ARFCOS": "Armed Forces Courier Service",
    "ARFMS": "Air Reserve Forces Meritorious Service Medal",
    "ARFORSTAT": "Army force status reporting system",
    "ARFPC": "Army Reserve Forces Policy Committee",
    "ARHOC": "Army Housing Committee",
    "ARI": "Army Research Institute",
    "ARIS": "advanced range instrumentation ship",
    "ARL": "authorized retention level",
    "ARLO": "air reconnaissance liaison officer",
    "ARM": "antiradiation missile; Army ready materiel",
    "ARMATSC": "Army Materiel Status Committees",
    "ARMDAS": "Army damage assessment system",
    "ARMEDASH": "armed advanced scout helicopter",
    "ARMGRD": "armed guard",
    "ARMIP": "accounting and reporting management improvement program",
    "ARMS": "Army Master Data File Retrieval Microform System",
    "armt": "armament"
  },
  "synonyms": {
    "appoint": [
      "designate",
      "detail",
      "assign",
      "select",
      "name",
      "task",
      "appointing authority"
    ],
    "investigation": [
      "administrative investigation",
      "AR 15-6 investigation",
      "fact-finding inquiry",
      "informal investigation",
      "formal investigation",
      "command-directed inquiry"
    ],
    "soldier": [
      "service member",
      "troop",
      "unit member",
      "reserve soldier",
      "guardsman"
    ],
    "unit": [
      "organization",
      "command",
      "element",
      "company-level element",
      "battalion-level unit"
    ],
    "commander": [
      "commanding officer",
      "CDR",
      "command authority",
      "appointing authority",
      "senior leader"
    ],
    "order": [
      "directive",
      "instruction",
      "tasking",
      "mission",
      "written order"
    ],
    "training": [
      "instruction",
      "professional development",
      "readiness event",
      "drill",
      "military training",
      "PME"
    ],
    "discipline": [
      "corrective action",
      "adverse action",
      "administrative action",
      "disciplinary measure"
    ],
    "policy": [
      "guidance",
      "directive policy",
      "command policy",
      "standard operating guidance"
    ],
    "meeting": [
      "briefing",
      "update",
      "synch meeting",
      "staff huddle",
      "coordination meeting"
    ]
  }
}
